rocketchat_async/.gitignore
rocketchat_async/__init__.py
rocketchat_async/constants.py
rocketchat_async/core.py
rocketchat_async/dispatcher.py
rocketchat_async/methods.py
rocketchat_async-4.3.0.dist-info/METADATA
rocketchat_async-4.3.0.dist-info/WHEEL
rocketchat_async-4.3.0.dist-info/licenses/LICENSE
rocketchat_async-4.3.0.dist-info/RECORD
