Metadata-Version: 2.4
Name: rocketchat-async
Version: 4.3.0
Summary: asyncio-based Python wrapper for the Rocket.Chat Realtime API.
License: MIT
License-File: LICENSE
Author: Hynek Urban
Author-email: hynek.urban@gmail.com
Requires-Python: >=3.7
Classifier: License :: OSI Approved :: MIT License
Classifier: Programming Language :: Python :: 3
Classifier: Programming Language :: Python :: 3.7
Classifier: Programming Language :: Python :: 3.8
Classifier: Programming Language :: Python :: 3.9
Classifier: Programming Language :: Python :: 3.10
Classifier: Programming Language :: Python :: 3.11
Classifier: Programming Language :: Python :: 3.12
Classifier: Programming Language :: Python :: 3.13
Classifier: Programming Language :: Python :: 3.14
Requires-Dist: websockets (>=10.4,<11.0)
Project-URL: Documentation, https://github.com/hynek-urban/rocketchat-async
Project-URL: Homepage, https://github.com/hynek-urban/rocketchat-async
Project-URL: Repository, https://github.com/hynek-urban/rocketchat-async
